etcd_config
