Metadata-Version: 1.1
Name: etcd-config
Version: 1.0.4
Summary: A dynamic settings management solution using ETCD
Home-page: https://github.com/kpn-digital/py-etcd-config
Author: Andrey Makhnach
Author-email: andrey.makhnach@kpn.com
License: UNKNOWN
Platform: UNKNOWN
Classifier: Development Status :: 5 - Production/Stable
Classifier: Environment :: Web Environment
Classifier: Intended Audience :: Developers
Classifier: Operating System :: OS Independent
Classifier: Programming Language :: Python
Classifier: Programming Language :: Python :: 2.7
Classifier: Programming Language :: Python :: 3.5
Classifier: Programming Language :: Python :: 3.6
Classifier: Topic :: Internet :: WWW/HTTP
